MANIFEST.in
README.md
setup.py
./variables
stackstage/__init__.py
stackstage/__main__.py
stackstage.egg-info/PKG-INFO
stackstage.egg-info/SOURCES.txt
stackstage.egg-info/dependency_links.txt
stackstage.egg-info/top_level.txt
stackstage/main/myclass.py
stackstage/main/parser.py