Metadata-Version: 2.1
Name: stackstage
Version: 0.80.75
Summary: Managing CloudFormation stacks
Home-page: https://github.com/LINKIT-Group/stackstage
Author: Anthony Potappel
Author-email: anthony.potappel@gmail.com
License: UNKNOWN
Platform: UNKNOWN
Classifier: Operating System :: POSIX :: Linux
Classifier: License :: OSI Approved :: MIT License
Classifier: Programming Language :: Python :: 3.5
Classifier: Programming Language :: Python :: 3.6
Classifier: Programming Language :: Python :: 3.7
